{"mid":5109,"trimyears":[{"y":2019,"trims":[{"status":1,"tid":140561,"tname":"325T 双离合欣悦版","price":10.49},{"status":1,"tid":140562,"tname":"325T 双离合欣尚版","price":11.49},{"status":1,"tid":140564,"tname":"320 手动欣悦版","price":9.09},{"status":1,"tid":140563,"tname":"320 手动欣享版","price":7.99},{"status":1,"tid":140566,"tname":"320 自动欣悦版","price":9.99},{"status":1,"tid":140565,"tname":"320 自动欣享版","price":8.89},{"status":1,"tid":140567,"tname":"320 自动欣尚版","price":10.99}]},{"y":2018,"trims":[{"status":1,"tid":139229,"tname":"1.5L 自动欣享版（天窗）","price":9.09},{"status":1,"tid":139227,"tname":"1.5L 手动欣享版","price":7.99},{"status":1,"tid":139228,"tname":"1.5L 自动欣享版","price":8.89},{"status":1,"tid":139230,"tname":"1.5L 手动欣悦版","price":9.09},{"status":1,"tid":139231,"tname":"1.5L 自动欣悦版","price":9.99},{"status":1,"tid":139232,"tname":"1.5L 自动欣尚版","price":10.99}]},{"y":2016,"trims":[{"status":-1,"tid":134509,"tname":"1.5L 手动欣享版","price":7.99},{"status":-1,"tid":134510,"tname":"1.5L 手动欣悦版","price":9.09},{"status":-1,"tid":134513,"tname":"1.5L 自动欣尚版","price":10.99},{"status":-1,"tid":134512,"tname":"1.5L 自动欣悦版","price":9.99},{"status":-1,"tid":134511,"tname":"1.5L 自动欣享版","price":8.89}]}]}