{"mid":4554,"trimyears":[{"y":2018,"trims":[{"status":1,"tid":141591,"tname":"1.9T 柴油自动四驱旗舰版 7座","price":16.38},{"status":1,"tid":140996,"tname":"1.9T 柴油自动两驱旗舰版 7座","price":14.98},{"status":1,"tid":140995,"tname":"2.4L 汽油手动四驱旗舰型 7座","price":11.98},{"status":1,"tid":140994,"tname":"2.4L 汽油手动两驱旗舰版 7座","price":10.88}]},{"y":2017,"trims":[{"status":-2,"tid":136506,"tname":"1.9T 柴油两驱豪华版 5座","price":11.98},{"status":-1,"tid":136509,"tname":"1.9T 柴油四驱豪华版 5座","price":13.48},{"status":-1,"tid":136401,"tname":"1.9T 柴油两驱豪华版 7座","price":12.38},{"status":-1,"tid":136402,"tname":"1.9T 柴油两驱旗舰版 7座","price":12.98},{"status":-1,"tid":136403,"tname":"1.9T 柴油四驱豪华版 7座","price":13.88},{"status":-1,"tid":136510,"tname":"1.9T 柴油四驱旗舰版 5座","price":14.08},{"status":-1,"tid":136404,"tname":"1.9T 柴油四驱旗舰版 7座","price":14.48},{"status":-1,"tid":136507,"tname":"1.9T 柴油两驱旗舰版 5座","price":12.58},{"status":-1,"tid":137570,"tname":"2.0T 汽油两驱豪华版 7座","price":11.68},{"status":-1,"tid":137572,"tname":"2.0T 汽油两驱旗舰版 7座","price":12.58},{"status":-1,"tid":137574,"tname":"2.0T 汽油四驱旗舰版 7座","price":14.08},{"status":-2,"tid":137569,"tname":"2.0T 汽油两驱豪华版 5座","price":11.38},{"status":-1,"tid":137573,"tname":"2.0T 汽油四驱豪华版 7座","price":13.48},{"status":-2,"tid":137571,"tname":"2.0T 汽油两驱旗舰版 5座","price":12.18}]},{"y":2016,"trims":[{"status":-1,"tid":135151,"tname":"1.9T 柴油两驱精英版 5座","price":10.38},{"status":-1,"tid":133644,"tname":"2.4L 汽油四驱精英型 5座","price":10.88},{"status":-1,"tid":133643,"tname":"2.4L 汽油两驱标准型 ","price":8.98},{"status":-1,"tid":135152,"tname":"2.4L 汽油两驱精英版 7座","price":9.08}]},{"y":2015,"trims":[{"status":-1,"tid":127563,"tname":"1.9T 柴油两驱标准型 ","price":12.28},{"status":-1,"tid":127677,"tname":"1.9T 柴油四驱豪华型 ","price":14.88},{"status":-1,"tid":127564,"tname":"1.9T 柴油两驱豪华型 ","price":13.28},{"status":-1,"tid":127562,"tname":"2.4L 汽油两驱豪华型 ","price":11.98},{"status":-1,"tid":127676,"tname":"2.4L 汽油四驱豪华型 ","price":13.58},{"status":-1,"tid":127561,"tname":"2.4L 汽油两驱标准型 ","price":10.98}]}]}