{"mid":4880,"trimyears":[{"y":2016,"trims":[{"status":1,"tid":132286,"tname":"2.2L豪华型长轴JM491Q-ME","price":6.7},{"status":1,"tid":132284,"tname":"2.2L豪华型短轴JM491Q-ME","price":6.6},{"status":1,"tid":132285,"tname":"2.2L舒适型长轴JM491Q-ME","price":6.64},{"status":1,"tid":132283,"tname":"2.2L舒适型短轴JM491Q-ME","price":6.54},{"status":1,"tid":132282,"tname":"2.8T豪华型长轴JE493ZQ8","price":7.78},{"status":1,"tid":132280,"tname":"2.8T豪华型短轴JE493ZQ8","price":7.68},{"status":1,"tid":132279,"tname":"2.8T舒适型短轴JE493ZQ8","price":7.62},{"status":1,"tid":132281,"tname":"2.8T舒适型长轴JE493ZQ8","price":7.72}]},{"y":2015,"trims":[{"status":-1,"tid":130711,"tname":"2.2L豪华版长轴JM491Q-ME","price":6.69},{"status":-1,"tid":130710,"tname":"2.2L标准版长轴JM491Q-ME","price":6.58},{"status":-1,"tid":130709,"tname":"2.2L豪华版短轴JM491Q-ME","price":6.59},{"status":-1,"tid":130708,"tname":"2.2L标准版短轴JM491Q-ME","price":6.48},{"status":-1,"tid":130707,"tname":"2.8T豪华版长轴JE493ZQ8","price":8.58},{"status":-1,"tid":130705,"tname":"2.8T豪华版短轴JE493ZQ8","price":8.48},{"status":-1,"tid":130704,"tname":"2.8T标准版短轴JE493ZQ8","price":8.18},{"status":-1,"tid":130706,"tname":"2.8T标准版长轴JE493ZQ8","price":8.28}]}]}